filecoin_lotus/__init__.py
filecoin_lotus/chain.py
filecoin_lotus/encoding.py
filecoin_lotus/filecoin.py
filecoin_lotus/gas.py
filecoin_lotus/mpool.py
filecoin_lotus/providers.py
filecoin_lotus/rpc_abi.py
filecoin_lotus/state.py
filecoin_lotus/types_check.py
filecoin_lotus/types_fil.py
filecoin_lotus/wallet.py
filecoin_lotus/utils/__init__.py
filecoin_lotus/utils/common.py
filecoin_lotus/utils/pubkey_to_address.py
filecoin_lotus/utils/transaction.py
nobi_filecoin_lotus-1.2.4.dist-info/LICENSE
nobi_filecoin_lotus-1.2.4.dist-info/METADATA
nobi_filecoin_lotus-1.2.4.dist-info/WHEEL
nobi_filecoin_lotus-1.2.4.dist-info/top_level.txt
nobi_filecoin_lotus-1.2.4.dist-info/RECORD
