Metadata-Version: 2.1
Name: nobi-filecoin-lotus
Version: 1.2.4
Summary: A package interact with bitcoin node
Home-page: https://github.com/nobbennob/nobi-filecoin-lotus
Author: Wen
Author-email: wenqinchao@gmail.com
License: MIT
Classifier: Programming Language :: Python :: 3
Classifier: License :: OSI Approved :: MIT License
Classifier: Operating System :: OS Independent
Requires-Python: >=3.6
License-File: LICENSE
Requires-Dist: requests
Requires-Dist: pycoin
Requires-Dist: cryptos
Requires-Dist: cbors
Requires-Dist: secp256k1
